hxrate/__init__.py
hxrate/backexchange.py
hxrate/hxdata.py
hxrate/methods.py
hxrate/openfe.py
hxrate/ratefit.py
hxrate-1.0.1.dist-info/LICENSE
hxrate-1.0.1.dist-info/METADATA
hxrate-1.0.1.dist-info/WHEEL
hxrate-1.0.1.dist-info/top_level.txt
hxrate-1.0.1.dist-info/RECORD
