Metadata-Version: 2.1
Name: hxrate
Version: 1.0.1
Summary: HX Rate Fitting
Author-email: SD <suggie@northwestern.edu>
Classifier: Programming Language :: Python :: 3
Classifier: License :: OSI Approved :: MIT License
Classifier: Operating System :: OS Independent
Requires-Python: >=3.9
License-File: LICENSE
Requires-Dist: matplotlib (==3.3.4)
Requires-Dist: numpy (==1.20.2)
Requires-Dist: numpyro (==0.8.0)
Requires-Dist: pandas (==1.2.5)
Requires-Dist: scikit-learn (==0.24.2)
Requires-Dist: scipy (==1.6.2)
Requires-Dist: pyyaml (==6.0)
Requires-Dist: biopython (==1.79)
Requires-Dist: molmass (==2021.6.18)
Requires-Dist: jax (==0.2.25)
Requires-Dist: jaxlib (==0.1.74)
Requires-Dist: psutil (==5.8.0)
